{
 "ceb": {
  "a": "a",
  "abante": "lead",
  "abdel": "abdel",
  "accords": "accords",
  "account": "account",
  "acute": "acute",
  "adirondaks": "adirondacks",
  "adlaw": "day",
  "aduna'y": "there",
  "adunahan": "rich",
  "adunay": "there",
  "advisory": "advisory",
  "aghimo": "do",
  "agos": "outflow",
  "agosto": "august",
  "agriculture": "agriculture",
  "agusto": "augustus",
  "ahmad": "ahmad",
  "akawnt": "account",
  "al": "yes",
  "alagad": "disciple",
  "alang": "for",
  "albania": "albania",
  "alpha": "alpha",
  "alps": "alps",
  "amihanan": "north",
  "amihang": "northern",
  "aming": "our",
  "among": "our",
  "an": "the",
  "anak": "son",
  "anan": "where",
  "and": "and",
  "ang": "the",
  "angitaa": "look for",
  "anhui": "anhui",
  "ani": "yield",
  "antiviral": "antiviral",
  "anwa": "how",
  "apan": "but",
  "apil": "including",
  "apod": "distributed",
  "appearance": "appearance",
  "aprobahan": "approve",
  "arabiko": "arabic",
  "arabo": "arabs",
  "arabong": "arab",
  "arafat": "arafat",
  "area": "area",
  "arkeolohikanhong": "archaeological",
  "armadong": "armed",
  "aron": "to",
  "arte": "art",
  "artikulo": "article",
  "asiryanhon": "assyrian",
  "astrazeneca": "astrazeneca",
  "asya": "asia",
  "at": "and",
  "atong": "our",
  "attractions": "attractions",
  "atubang": "handle",
  "aviv": "aviv",
  "aw": "wow",
  "awa": "pity",
  "awtopsiya": "autopsy",
  "awtoridad": "authorities",
  "ayoha": "fix",
  "baba": "chin",
  "babae": "woman",
  "babilonyanhon": "babylonians",
  "bachawa": "poor",
  "bag": "handbag",
  "bahasa": "in",
  "bahin": "about",
  "bakuna": "vaccine",
  "balita": "news",
  "bana": "husband",
  "banda": "band",
  "bandila": "flag",
  "bangyaw": "hoohëö'o",
  "bank": "bank",
  "barangay": "village",
  "baranggay": "village",
  "baroganan": "convictions",
  "baruganan": "principles",
  "basa": "wet",
  "basaha": "read",
  "basehan": "basis",
  "basihan": "basis",
  "batok": "against",
  "bayograpiya": "biographies",
  "bayrus": "viruses",
  "beijing": "beijing",
  "bian": "yes",
  "bilyon": "billion",
  "bing": "bing",
  "binikol": "bmikól",
  "binisaya": "bisaya",
  "binosniyo": "married",
  "binyeloruso": "viniloruso",
  "binyetnamita": "vietnamese",
  "biomass": "biomass",
  "biontech": "biotech",
  "biosphere": "biosphere",
  "bisan": "although",
  "bisrock": "bisrock",
  "blakbord": "blackboard",
  "body": "body",
  "border": "border",
  "boreal": "boreal",
  "bosanski": "bosnian",
  "bud": "bud",
  "bulan": "months",
  "buot": "wanted",
  "butangi'g": "put it",
  "by": "by",
  "bú": "boo",
  "c": "c",
  "can": "can",
  "canaan": "where",
  "cantones": "cantons",
  "capital": "capital",
  "cebuano": "version",
  "cest": "this",
  "cet": "cet",
  "chairman": "chairman",
  "charter": "charter",
  "chengzhong": "chengzhong",
  "chhī": "chhī",
  "chia": "chia",
  "china": "china",
  "chinese": "chinese",
  "chongqing": "chongqing",
  "chou": "chou",
  "close": "close",
  "cn": "cn",
  "code": "code",
  "coma": "coma",
  "commons": "commons",
  "compound": "compound",
  "conflict": "conflict",
  "control": "control",
  "controlado": "controlled",
  "controlled": "controlled",
  "coordinates": "coordinates",
  "copyright": "copyright",
  "coronavirus": "coronavirus",
  "council": "council",
  "country": "country",
  "covid": "covid",
  "ct": "ct",
  "curfew": "curfew",
  "curfews": "curfew",
  "cymraeg": "welsh",
  "da": "yes",
  "daghan": "many",
  "daghang": "many",
  "dagkong": "major",
  "dahil": "due",
  "dakbayan": "city",
  "dako": "great",
  "damgo": "dream",
  "damuchang": "dust",
  "dapit": "sites",
  "date": "date",
  "dawlat": "state",
  "dayon": "then",
  "dayt": "date",
  "de": "of",
  "dekadang": "decades",
  "densidad": "density",
  "density": "density",
  "didto": "there",
  "dihang": "when",
  "diin": "where",
  "diksiyonaryo": "dictionary",
  "dinhi": "here",
  "diplomat": "diplomat",
  "disease": "disease",
  "display": "display",
  "distance": "distance",
  "distansya": "distance",
  "distress": "distress",
  "disyembre": "december",
  "diyalekto": "dialect",
  "dokumento": "documents",
  "dominanteng": "dominant",
  "don't": "don't",
  "donasyon": "donations",
  "dongjin": "dongjin",
  "dst": "etc",
  "duha": "both",
  "dunay": "there",
  "duol": "by",
  "duzhenwan": "duzhenwan",
  "e": "yes",
  "earth": "earth",
  "eastern": "eastern",
  "ebidensya": "evidence",
  "ecological": "ecological",
  "ecosystem": "ecosystem",
  "ecozones": "ecozones",
  "edad": "age",
  "edit": "edit",
  "eesti": "estonia",
  "ehipto": "egypt",
  "ekolohiyanhong": "ecological",
  "ekonomikanhon": "economic",
  "ekonomiya": "economy",
  "ekosistema": "ecosystems",
  "ekperensyang": "experience",
  "eksisting": "existing",
  "ektarya": "hectare",
  "elections": "elections",
  "embahada": "embassy",
  "embassy": "embassy",
  "emergency": "emergency",
  "enact": "enact",
  "enclaves": "enclaves",
  "enero": "january",
  "enery": "energy",
  "ensiklopedya": "encyclopedia",
  "equator": "equator",
  "eskuylahan": "schools",
  "español": "espanol",
  "espeling": "spelling",
  "espisye": "species",
  "estado": "state",
  "estadong": "states",
  "estudyante": "students",
  "exercise": "exercise",
  "extended": "extended",
  "fatah": "fatah",
  "filastiniyyah": "palestine",
  "file": "file",
  "first": "first",
  "food": "food",
  "for": "for",
  "forest": "forest",
  "foundation": "foundation",
  "ft": "feet",
  "function": "function",
  "galamiton": "utensils",
  "galego": "galician",
  "gamhanan": "master",
  "gamiton": "use",
  "ganahan": "i",
  "ganghaan": "gates",
  "gatos": "cat",
  "gatosan": "hundreds",
  "gawas": "apart",
  "gawasnong": "free",
  "gayod": "really",
  "gaza": "gas",
  "geheyan": "bed",
  "geonames": "geonames",
  "geopolitical": "geopolitical",
  "geputan": "get ready",
  "gi": "ghee",
  "gibana": "approximately",
  "gidasig": "encourage",
  "gigamit": "used",
  "gigikanan": "origin",
  "gihabogon": "height",
  "gihapon": "still",
  "gihimo": "done",
  "giilog": "captured",
  "giingon": "what",
  "giiniton": "heated",
  "gikan": "from",
  "gikontrol": "controlled",
  "gikumpirma": "confirmed",
  "gimandoan": "directed",
  "gimugna": "created",
  "ginagamit": "used",
  "ginagmay": "petty",
  "ginales": "polished",
  "ginalyego": "lying down",
  "gipahibalo": "office has partnered",
  "gipahimutang": "installed",
  "gipanag": "owned",
  "gipangbuhat": "did",
  "gipili": "choose",
  "giproklamar": "proclaimed",
  "gipuy": "inhabited",
  "gisugdan": "begins",
  "gisulayan": "tested",
  "gisundan": "followed",
  "gisuportahan": "supported",
  "gitaa": "written",
  "gitabonan": "concealed",
  "gitan": "ghetto",
  "gitas": "height",
  "gitawag": "called",
  "gitukod": "organized",
  "giusab": "change",
  "giutlanan": "bordering",
  "gmt": "gmt",
  "goberno": "government",
  "golan": "goal",
  "google": "google",
  "government": "government",
  "gross": "gross",
  "grupo": "group",
  "gònghéguó": "gonghéguó",
  "habagatan": "south",
  "habagatang": "south",
  "habog": "great",
  "hamas": "hammer",
  "hamtong": "adults",
  "han": "wo",
  "hapit": "almost",
  "hb": "hb",
  "health": "health",
  "heights": "heights",
  "help": "help",
  "henan": "henan",
  "herusalen": "jerusalem",
  "heyograpiya": "geography",
  "hikapon": "touch",
  "hilabihan": "much",
  "hilanat": "fever",
  "hilig": "interests",
  "hinabanes": "smoothed",
  "hinloa": "purify",
  "hinubad": "translated",
  "hinungdan": "cause",
  "hinuon": "however",
  "hisgot": "discussion",
  "holy": "holy",
  "hon": "hello",
  "hongzhong": "hongzhong",
  "hordanya": "jordan",
  "hordyan": "horde",
  "hsien": "hsien",
  "hu": "shoo",
  "hubei": "hubei",
  "hudiyo": "jew",
  "hudíyo": "jew",
  "hulagway": "picture",
  "hulga": "threats",
  "hulyo": "july",
  "human": "by",
  "hunan": "hunan",
  "hunyo": "june",
  "hupeh": "huffy",
  "husseini": "husseini",
  "hàn": "wo",
  "hànyǔ": "hànyǔ",
  "i": "i",
  "iata": "here",
  "ideya": "ideas",
  "ika": "th",
  "ikatulong": "fourth",
  "iladong": "popular",
  "ilahang": "their",
  "ilalom": "below",
  "ilegal": "illegal",
  "illegal": "illegal",
  "imbensyon": "invention",
  "imong": "your",
  "imperyo": "empire",
  "impluwensya": "influences",
  "inarabigo": "arabic",
  "indibidwal": "individual",
  "indya": "india",
  "inebreo": "ebreu",
  "inestonyo": "estonian",
  "infobox": "infobox",
  "ingon": "as",
  "iniloko": "fooled",
  "ininggles": "english",
  "iningles": "mercado",
  "inintsek": "chinese script",
  "inintsik": "chinese",
  "inislandes": "icelandic",
  "inoksitano": "inoxidable",
  "internet": "internet",
  "intsik": "chinese",
  "inubanan": "fully",
  "inusara": "alone",
  "inusarang": "single",
  "isip": "mind",
  "iso": "dog",
  "israel": "israel",
  "israeli": "israeli",
  "isrā'īl": "isra'il",
  "istasyon": "stations",
  "italya": "italy",
  "iwan": "leave behind",
  "iya": "his",
  "iyang": "his",
  "jacob": "jacob",
  "january": "january",
  "jawa": "java",
  "jiangxi": "jiangxi",
  "june": "june",
  "ka": "you",
  "kaagi": "past",
  "kaayong": "great",
  "kabalayan": "houses",
  "kabisay": "visayas",
  "kabukirang": "mountains",
  "kabungtoran": "hills",
  "kada": "each",
  "kadaghanan": "many",
  "kadaghnan": "abundance",
  "kadugayan": "eventually",
  "kagamhanan": "powers",
  "kagawasan": "freedom",
  "kagawasang": "liberation",
  "kagulangon": "first",
  "kahaboga": "height",
  "kahimsug": "health",
  "kahulugan": "definitions",
  "kalabotan": "involvement",
  "kalasangan": "forests",
  "kalasangang": "forest",
  "kalibotan": "world",
  "kalibutan": "the world",
  "kalibutanong": "worldly",
  "kalihokan": "activity",
  "kamatayon": "death",
  "kami": "we",
  "kaming": "we",
  "kamot": "hand",
  "kamulupyohan": "population",
  "kanasuran": "nations",
  "kang": "you",
  "kaniadto": "history",
  "kaniadtong": "on",
  "kanila": "them",
  "kantidad": "value",
  "kanunay": "ever",
  "kanunayng": "always",
  "kapanahonan": "times",
  "kapanguhaan": "resources",
  "kapin": "more",
  "kapital": "capital",
  "kapunongan": "order",
  "karaang": "ancient",
  "karera": "races",
  "karon": "today",
  "kasadpan": "western",
  "kasadpang": "west",
  "kasagaran": "for the most part",
  "kasagarang": "common",
  "kasarangan": "moderate",
  "kasarangang": "moderate",
  "kasaysayan": "background",
  "katalagmanong": "catastrophic",
  "katap": "widely",
  "katawhan": "people",
  "katawhang": "peoples",
  "katilingban": "community",
  "katitikan": "minutes",
  "katukoran": "structure",
  "kauban": "companions",
  "kaubang": "comrade",
  "kaugalingong": "own",
  "kaulohan": "capital",
  "kaumahan": "fields",
  "kay": "with",
  "kaylap": "widespread",
  "kilometro": "kilometer",
  "kin": "who",
  "kinabasaan": "reading",
  "kinabugnawan": "cold",
  "kinabuhi": "life",
  "kinadak": "largest",
  "kinadul": "nearest",
  "kinahabagathonang": "southernmost",
  "kinahabogang": "highest",
  "kinahanglanon": "requirements",
  "kinainitan": "warmest",
  "kinapampangan": "the most beautiful",
  "kinataas": "highest",
  "kinatsila": "spanish",
  "kinaugahan": "driest",
  "kingdom": "kingdom",
  "kining": "this",
  "kinsa": "who",
  "klima": "climate",
  "km": "km",
  "kml": "kml",
  "knesset": "knesset",
  "komposisyon": "composition",
  "kompyuter": "computer",
  "komunidad": "community",
  "kon": "when",
  "konifer": "conifer",
  "konpederasyon": "confederate",
  "kontaka": "contact",
  "kontrobersyal": "controversial",
  "koordinasyon": "coordination",
  "korea": "korea",
  "koronabayrus": "coronavirus",
  "kun": "or",
  "kuwarentay": "forty",
  "kuwarentina": "quarantine",
  "kwadrado": "meters",
  "la": "only",
  "labaw": "surpassing",
  "lain": "other",
  "laing": "another",
  "lainlain": "variety",
  "lakang": "steps",
  "lakip": "among",
  "lalaki": "men",
  "lalawigan": "province",
  "lanaw": "shallow pool",
  "land": "nilly",
  "lang": "only",
  "large": "large",
  "lasang": "forest",
  "lat": "lat",
  "latina": "latin",
  "latitudes": "latitude",
  "latviešu": "latvian",
  "lawas": "body",
  "leader": "leader",
  "legal": "legally",
  "levant": "levant",
  "li": "what",
  "libano": "lebanon",
  "liberación": "liberacion",
  "liberation": "liberation",
  "libre": "free",
  "libreng": "free",
  "libro": "book",
  "ligang": "miss of one's step over smth",
  "linatin": "latin",
  "lineton": "lineton",
  "lingkoranan": "litter",
  "listahan": "list",
  "lokal": "local",
  "long": "long",
  "loves": "loves",
  "lugar": "place",
  "lumad": "native",
  "lungsod": "city",
  "luwas": "safe",
  "lán": "only",
  "m": "m",
  "maaari": "can",
  "maapod": "clan",
  "maayong": "good",
  "mag": "to",
  "magpasabot": "mean",
  "magtatambal": "physician",
  "mahimo": "can",
  "mahimong": "be",
  "mahitungod": "about",
  "mailhi": "unknown",
  "maisip": "conceive",
  "makaapekto": "affect",
  "makahikap": "touches",
  "makatabang": "help",
  "makontak": "contacted",
  "malikayan": "avoided",
  "mandarin": "mandarin",
  "manggugubat": "warriors",
  "manila": "prey",
  "mao": "is",
  "mao'y": "yeah",
  "maong": "jeans",
  "mapagawas": "released",
  "maporma": "condensation",
  "maps": "maps",
  "mapugngan": "prevent",
  "mapugong": "can be prevented",
  "marso": "march",
  "martir": "martyr",
  "mas": "more",
  "matag": "every",
  "matematika": "mathematics",
  "matin": "to taste",
  "matinabangon": "helpful",
  "matino": "sober",
  "matuod": "granted",
  "may": "with",
  "mayo": "may",
  "mayor": "mayor",
  "medinat": "medina",
  "mediteraneo": "mediterranean",
  "medya": "media",
  "medyo": "somewhat",
  "melayu": "malay",
  "mensahe": "messages",
  "messages": "messages",
  "meta": "goal",
  "metro": "meter",
  "metros": "meters",
  "mga": "the",
  "mi": "we",
  "miao": "meow",
  "miatake": "attacked",
  "midagan": "ran",
  "mideklarar": "declared",
  "mikaylap": "spread",
  "milantaw": "look",
  "milimetro": "millimeter",
  "militante": "militants",
  "million": "million",
  "milya": "miles",
  "milyon": "million",
  "milyones": "million",
  "mimaropa": "appeared",
  "min": "min",
  "minalayo": "motorcycles",
  "ministro": "minister",
  "mipahayag": "states",
  "mipakita": "shows",
  "mismong": "particular",
  "misugod": "began",
  "misulod": "entering",
  "misunod": "follows",
  "mitan": "looks",
  "mitubo": "grow",
  "mitukod": "builds",
  "miyerkules": "wednesday",
  "mobalhin": "move",
  "mograbe": "worse",
  "mohammed": "mohammed",
  "mohatag": "give",
  "mokaylap": "spread",
  "molupyo": "resident",
  "mopakigbahin": "shares",
  "mosunod": "obey",
  "mouyon": "disagree",
  "munazzamat": "i am sorry",
  "munisipyo": "municipal",
  "n": "n",
  "na": "that",
  "naaprobahan": "approved",
  "nag": "site",
  "nagapadagan": "running",
  "naggamit": "exercises",
  "naghatag": "gives",
  "nagkahinungdan": "caused",
  "nagkalainlaing": "various",
  "naglakip": "includes",
  "naglangkob": "comprising",
  "naglukop": "pervasive",
  "nagpadayon": "continues",
  "nagplano": "plans",
  "nagse": "saving",
  "nagsugod": "begins",
  "nagtuo": "believe",
  "nahibaw": "found out",
  "nahimo": "done",
  "nahimong": "becomes",
  "nahimutang": "nestled",
  "nahimutangan": "location",
  "nailhan": "identified",
  "nakaapekto": "affect",
  "nakadaog": "have",
  "nakadawat": "receives",
  "nakakuha": "already received",
  "nakasira": "downfall",
  "nakigbisog": "struggling",
  "nakigdait": "peace",
  "nalukop": "full",
  "namatay": "died",
  "namatikdan": "the audience",
  "nanang": "pus",
  "nangabot": "arrive",
  "nangulo": "leads",
  "napabilin": "remained",
  "napuloan": "tens",
  "naredirek": "redirected",
  "nasakit": "sick",
  "nasod": "nations",
  "nasodnnong": "national",
  "nasodnong": "national",
  "nasora": "country",
  "nasud": "nation",
  "nasudnon": "national",
  "nasudnong": "national",
  "nataptan": "infected",
  "natawhan": "birthday",
  "natukod": "established",
  "nature": "nature",
  "nawala": "lost",
  "nawong": "face",
  "negatibo": "negative",
  "negosasyon": "negotiations",
  "ng": "of",
  "ngadto": "unto",
  "ngalan": "name",
  "ngan": "and",
  "ngaran": "namespace",
  "ni": "of",
  "niadtong": "those",
  "niay": "here",
  "niini": "this",
  "nilang": "nsome",
  "ninorwego": "norwegian",
  "niya": "he even",
  "nobel": "novel",
  "nobiyembre": "november",
  "norway": "norway",
  "nuybayork": "new york",
  "nynorsk": "nepali",
  "nâng": "when",
  "o": "or",
  "ob": "or",
  "occitan": "occitan",
  "occupied": "occupied",
  "oecd": "oecd",
  "of": "of",
  "og": "and",
  "oha": "oh, oh",
  "on": "on",
  "ong": "yes",
  "opisyal": "official",
  "or": "or",
  "organismo": "organism",
  "organización": "organization",
  "organization": "organization",
  "orihinal": "original",
  "oslo": "oslo",
  "ot": "oh",
  "other": "other",
  "otomano": "ottoman",
  "ou": "you",
  "oukiamiao": "okiamiao",
  "oumiao": "oumiao",
  "our": "our",
  "oxford": "oxford",
  "pa": "more",
  "paagi": "ways",
  "paboritong": "favorite",
  "padayo'g": "continue",
  "pag": "once",
  "pagbahin": "sneeze",
  "pagbahing": "sneezing",
  "pagbiyahe": "getting",
  "pagdawat": "receiving",
  "paggamit": "use",
  "pagginhawa": "breath",
  "paghatag": "giving",
  "paghimo": "make",
  "paghugas": "washing",
  "paghuman": "after",
  "pagkab": "achieve",
  "pagkachairman": "chairmanship",
  "pagkahuman": "completion",
  "pagkalat": "spreading",
  "pagkamatay": "death",
  "pagkansela": "cancellation",
  "pagkapalestinian": "palestinianness",
  "pagkasulat": "writing",
  "pagkasunod": "the next",
  "pagkatap": "spread",
  "pagkatukod": "foundation",
  "pagkaylap": "spread",
  "pagkuwarentinas": "quarantining",
  "paglabay": "after",
  "pagmintinar": "maintaining",
  "pagpakigbisog": "fought",
  "pagpalayo": "away",
  "pagpangatake": "attacks",
  "pagpugong": "controlling",
  "pagpuno": "fill",
  "pagpuyo": "live",
  "pagsara": "closing",
  "pagsaway": "reproving",
  "pagsira": "breaking",
  "pagsugot": "compliance",
  "pagsul": "wearing",
  "pagsulat": "writing",
  "pagsuporta": "supporting",
  "pagtabon": "cover",
  "pagtahod": "respect",
  "pagtulo": "leaking",
  "pakisayran": "references",
  "paksyon": "factions",
  "palesitinho": "palestino",
  "palestina": "palestine",
  "palestine": "palestine",
  "palestinhon": "palestinians",
  "palestinhong": "palestinian",
  "palestinian": "palestinian",
  "pampang": "shore",
  "pamúo": "construction",
  "panaghisgot": "discussions",
  "panagsumpaki": "controversy",
  "panagsungi": "conflict",
  "panahon": "period",
  "panambal": "therapy",
  "panapton": "headdress",
  "pandemik": "pandemic",
  "pandemya": "pandemic",
  "pang": "more",
  "panghitabo": "events",
  "pangitaa": "look",
  "panglantaw": "view",
  "panglawas": "health",
  "pangmasang": "mass",
  "pangulo": "president",
  "panid": "page",
  "panindota": "enhance",
  "paningkamot": "efforts",
  "pantabon": "cover",
  "panuigon": "old",
  "para": "for",
  "parliamentaryo": "parliamentary",
  "partido": "party",
  "partidong": "party",
  "parties": "parties",
  "party": "party",
  "pasahero": "passenger",
  "pasilidad": "facilities",
  "pasuguan": "embassy",
  "pasyente": "patient",
  "patag": "plain",
  "peace": "peace",
  "pebrero": "february",
  "pei": "pay",
  "peres": "pear",
  "pfizer": "pfizer",
  "photos": "photos",
  "pila": "lineup",
  "pilipinas": "philippines",
  "pilosopiya": "philosophy",
  "pinaagi": "through",
  "pinanggasinan": "fueled",
  "pinansyal": "finance",
  "piniling": "chosen",
  "pinlandes": "finnish",
  "pinortuges": "portuguese",
  "pinulongan": "languages",
  "pinulongang": "language",
  "pinuy": "environment",
  "pinyin": "pinyin",
  "pipila": "some",
  "plo": "pl",
  "pneumonia": "pneumonia",
  "politikal": "political",
  "politikanhong": "political",
  "popular": "popular",
  "populasyon": "population",
  "population": "population",
  "porsyento": "percentage",
  "positibo": "positive",
  "post": "post",
  "poste": "pole",
  "postponement": "postponement",
  "prc": "prc",
  "prize": "prize",
  "problema": "problem",
  "produksyon": "productivity",
  "province": "province",
  "proyekto": "project",
  "pst": "p.s",
  "public": "public",
  "publikong": "public",
  "pula": "red",
  "pundok": "organization",
  "punong": "chief",
  "pwede": "-pwede",
  "qiliping": "qiliping",
  "qingling": "qingling",
  "qu": "what",
  "quarantines": "quarantine",
  "qudwa": "qudwa",
  "quotes": "quotes",
  "ra": "only",
  "rabin": "rabbi",
  "rahman": "rahman",
  "ramallah": "ramallah",
  "raouf": "rauf",
  "rehiyon": "regions",
  "rekonosidong": "recognized",
  "republic": "republic",
  "republika": "republic",
  "república": "republic",
  "resolution": "resolution",
  "respiratory": "respiratory",
  "river": "river",
  "romano": "roman",
  "romblon": "romblon",
  "rpt": "rpt",
  "rénmín": "renmin",
  "sab": "also",
  "sagolsagol": "mixed",
  "sakit": "diseases",
  "sakop": "subjects",
  "sama": "like",
  "samtang": "while",
  "sauna": "sauna",
  "saysay": "dismissed",
  "screening": "screening",
  "sebwano": "cebuano",
  "secretary": "secretary",
  "security": "security",
  "sentro": "center",
  "serber": "server",
  "serbisyo": "services",
  "shaanxi": "shaanxi",
  "shan": "shan",
  "share": "share",
  "sheng": "sheng",
  "shi": "shi",
  "shih": "shih",
  "shimon": "simon",
  "shuiku": "shuiku",
  "shuqeiri": "shuqeiri",
  "si": "if",
  "sibilisasyon": "civilization",
  "sibilyan": "civilian",
  "sidlakan": "east",
  "sidlakang": "east",
  "sila": "they",
  "simple": "simple",
  "simtomas": "symptom",
  "sino": "jeepney",
  "sinugboanong": "english",
  "sinugdanan": "beginning",
  "sinulat": "writings",
  "siria": "syrian",
  "sistema": "system",
  "sistemang": "system",
  "siya": "he",
  "siyensiya": "science",
  "siyonismo": "zionism",
  "small": "small",
  "soberanya": "sovereignty",
  "social": "social",
  "speak": "speak",
  "sq": "sq",
  "standard": "standard",
  "state": "state",
  "strip": "strip",
  "suba": "river",
  "subdibisyon": "subdivision",
  "subtropikal": "subtropical",
  "sugod": "dash",
  "sugyot": "tips",
  "sukad": "from",
  "sulatonong": "written",
  "sulod": "contents",
  "sumala": "according",
  "sumbanan": "framework",
  "summer": "summer",
  "sumpay": "connect",
  "suod": "close",
  "suomi": "finnish",
  "suroyan": "walk",
  "susama": "like",
  "swiss": "switzerland",
  "syndrome": "syndrome",
  "sṳ": "sṳ",
  "taas": "height",
  "tagoa": "hide",
  "tagrepresentar": "representative",
  "tahrir": "tahrir",
  "talaan": "record",
  "tali": "leash",
  "taliwala": "amid",
  "tambal": "drugs",
  "tambong": "meet",
  "tan": "yes",
  "tanang": "all",
  "tanom": "flora",
  "taong": "year",
  "tawhanong": "human",
  "tawo": "people",
  "teknolohiya": "technology",
  "tel": "phone",
  "teritoryo": "territory",
  "terorrista": "terrorist",
  "terrestrial": "terrestrial",
  "text": "text",
  "the": "the",
  "them": "them",
  "tiandian": "to be compared",
  "tibetanhon": "tibetan",
  "tibuok": "around",
  "tien": "ten",
  "tiganos": "coordinate",
  "tigdumala": "operator",
  "tiggamit": "users",
  "tigsulti": "spokesperson",
  "tigtampohan": "contributors",
  "tigulang": "elderly",
  "timailhan": "signs",
  "time": "time",
  "timezone": "time zone",
  "tinagalog": "tsang",
  "tinakpan": "covered",
  "tinguha": "desire",
  "tinipong": "united",
  "tinubdan": "source",
  "tiếng": "language",
  "total": "total",
  "tourist": "tourist",
  "transition": "transition",
  "transmission": "transmission",
  "tren": "train",
  "tropikal": "tropical",
  "tsapter": "chapters",
  "tsina": "china",
  "tsinabakano": "chinese",
  "tubaan": "to be buried",
  "tubiganan": "water body",
  "tugpahanan": "airports",
  "tuig": "year",
  "tukmang": "appropriate",
  "tulunghaan": "a school",
  "tungang": "middle",
  "tungod": "because",
  "tśina": "china",
  "uban": "others",
  "ubang": "other",
  "ubo": "cough",
  "ubos": "under",
  "ug": "and",
  "ukranyano": "ukrainian",
  "ulan": "rain",
  "ulohan": "title",
  "umogon": "humid",
  "un": "one",
  "una": "first",
  "unaha": "keep",
  "unang": "first",
  "unibersidad": "university",
  "unified": "unified",
  "united": "united",
  "unsaon": "how",
  "until": "m",
  "upat": "four",
  "upload": "upload",
  "uropa": "europe",
  "usa": "deer",
  "usa'g": "one",
  "usab": "also",
  "usag": "one",
  "usba": "adjust",
  "uses": "uses",
  "utc": "utc",
  "utlanan": "boundary",
  "virus": "viruses",
  "việt": "vietnamese",
  "vujhan": "vujhan",
  "vú": "vu",
  "wala'y": "arbitrary",
  "walay": "no",
  "wang": "whang",
  "west": "west",
  "wide": "wide",
  "width": "width",
  "wiki": "wiki",
  "wikibooks": "wikibooks",
  "wikimedia": "wikipedia",
  "wikinews": "wikinews",
  "wikipedia": "wikipedia",
  "wikipedya": "wikipedia",
  "wikiquote": "wikipedia",
  "wikisource": "wikisource",
  "wikispecies": "wikispecies",
  "wikitext": "wikitext",
  "wikiversity": "wikiversity",
  "wiktionary": "wikipedia",
  "winaray": "finished",
  "world": "world",
  "wu": "wow",
  "wuh": "wow",
  "wuhan": "wuhan",
  "xian": "xian",
  "xiang": "xiang",
  "xianwang": "xianwang",
  "xiaogang": "xiaogang",
  "yangtze": "yangtze river",
  "yano": "homely",
  "yanong": "simply",
  "yasser": "yasser",
  "yazikou": "yazikou",
  "yellow": "yellow",
  "yichang": "yichang",
  "yiling": "yili",
  "yitzhak": "yitzhak",
  "you": "you",
  "your": "your",
  "yuta": "earth",
  "yutang": "land",
  "zhen": "zhen",
  "zhonglin": "zhonglin",
  "zhou": "zhou",
  "zhōngguó": "zhongguo",
  "zhōnghuá": "zhōnghuá",
  "zhōngwén": "zhongwen",
  "ziqiu": "ziqiu",
  "zone": "zone",
  "zougang": "zougang",
  "íslenska": "icelandic",
  "беларуская": "belarusian",
  "українська": "ukrainian",
  "ישראל": "israel",
  "ba": "bachelor of arts",
  "di": "drill instructor",
  "alana": "alan",
  "anaa": "available",
  "anang": "his",
  "arodi": "arod",
  "babaye": "woman",
  "balaan": "holy",
  "bantog": "celebrated",
  "batan": "young",
  "bayad": "fees",
  "başkası": "baskasi",
  "berde": "green",
  "binhi": "seed",
  "britanya": "britain",
  "bukid": "farm",
  "bálanan": "báilain",
  "calá": "calá",
  "dagat": "sea",
  "dahon": "leaf",
  "dakong": "great",
  "dili": "not",
  "eksiltmedi": "exiltmedi",
  "gilat": "nilat",
  "gubat": "woods",
  "heli-": "relating to helicopters",
  "hesron": "hezron",
  "higante": "giant",
  "higayon": "time",
  "hilagpos": "loosening",
  "hinabahaba": "length",
  "ibabaw": "surface",
  "iginulong": "roll",
  "igos": "fig",
  "ilang": "wilderness",
  "inapawan": "covered",
  "ipagaalis": "bring them",
  "ipakamit": "get",
  "ipanumpa": "dispute",
  "ipasusundo": "send",
  "jehova": "lord",
  "jehova-jireh": "jehovahjireh",
  "kaayo": "too",
  "kagutom": "hunger",
  "kahoy": "trees",
  "kalag": "loose",
  "kalaha": "pan",
  "kaluwangan": "breadth",
  "kamo": "you",
  "kaniya": "her",
  "kapatagan": "plains",
  "kaslohita": "kashohita",
  "katuyuan": "purpose",
  "kerubit": "chronicle",
  "kinatayuan": "lightened",
  "kini": "it",
  "kog": "i",
  "kollarını": "kollarini",
  "kolum": "column",
  "kombinasyon": "combination",
  "kopya": "copy",
  "kutsamasıyla": "tutsamasıyla",
  "labing": "more",
  "lagda": "signature",
  "lami": "taste",
  "libna": "lib'nah",
  "likay": "refill",
  "maagog": "sunset",
  "maayo": "good",
  "magbubo": "spill",
  "magbukid": "workers",
  "magdala": "bring",
  "magkabikabila": "side",
  "magkatalastasan": "each other",
  "maglililo": "falsely",
  "magpakalinis": "clean",
  "magpakasakdal": "magpasugdal",
  "magpalaanakin": "fruitful",
  "magpauna": "forestall",
  "magpéla": "refessor",
  "magsidami": "increased",
  "magsilago": "increasing",
  "magsiliko": "spin",
  "magsusugo": "send",
  "mahalon": "costly",
  "makakita": "see",
  "makakubusise": "makabusise",
  "makalinde": "visually",
  "makapito": "sevenfold",
  "makasangpu": "ten",
  "makita": "see",
  "mangabihag": "captivity",
  "mangagkaanak": "bear",
  "mangagpahinga": "relax",
  "mangbubukid": "farmer",
  "manguha": "gather",
  "mapula": "red",
  "matuo": "belie",
  "medikal": "medical",
  "mizpa": "mizpah",
  "nabuksan": "opens",
  "nagbuka": "opened",
  "nagdala": "carried",
  "nagkagutom": "famine",
  "nagkahapon": "evening",
  "nagkaumaga": "morning",
  "naglingkod": "sitting",
  "nagmalas": "looked",
  "nagpahihip": "didst",
  "nagpanata": "vow",
  "nagpanumpaan": "swore",
  "nagparaan": "passed",
  "nagpasugo": "sent",
  "nagsalitaan": "spake",
  "nagsibangon": "rise",
  "nagsihiga": "they lay",
  "nagsilayo": "gone",
  "nagsiliko": "turned",
  "nagsilulan": "entered",
  "nagsilunsad": "gone",
  "nagtuli": "circumcelled",
  "nakaina": "drained",
  "nakakita": "saw",
  "nakalatan": "overspread",
  "nalagot": "irritated",
  "nalango": "drunk",
  "nangagbalik": "backs",
  "nangagpangkatpangkat": "it is helpful",
  "nangagsikain": "they did",
  "nangagsilunsad": "went",
  "nangagsitingin": "looked",
  "nangahas": "durst",
  "nangamagama": "nagamagama",
  "nanganak": "birth",
  "nangayamot": "wearied",
  "napaitaas": "lifted",
  "napuno": "filled",
  "negeb": "negev",
  "nephtali": "naphtali",
  "nga": "that",
  "operasyon": "surgery",
  "pagaantok": "sleep",
  "pagka": "when",
  "pagkakita": "discernment",
  "pagkapananim": "kind",
  "pagkasumpong": "when",
  "pagtahan": "residency",
  "pagtawag": "call",
  "palibot": "surroundings",
  "pamalayu": "promise",
  "panapi": "aprons",
  "papagaanakin": "fruitful",
  "parang": "a malayan machete",
  "patuli": "decent",
  "pildir": "pill",
  "pilo": "fold",
  "pinakapagkain": "for eating",
  "pinakapilit": "strongly",
  "pisga": "pisgah",
  "preamp": "short for preamplifier",
  "pusta": "stakes",
  "puwa": "plectrum",
  "querubin": "cherubim",
  "rahatlayınca": "rahatayınca",
  "rehobot-ir": "rehoboth ir",
  "restriksiyon": "restrictions",
  "sa": "on",
  "sa-ra": "ra",
  "sabta": "answer",
  "sakong": "heel",
  "salapi": "cash",
  "sentromerler": "centromerler",
  "sibulan": "overgrow",
  "siclo": "shekel",
  "siklo": "shekel",
  "simron": "shimron",
  "subay": "along",
  "subong": "today",
  "sucot": "succoth",
  "sugo": "messenger",
  "sundang": "dagger",
  "tagsatzung": "tagatzung",
  "tahas": "outright",
  "talan": "view",
  "tigpipito": "sevens",
  "tiil": "foot",
  "tinapay": "bread",
  "tinuli": "circumcised",
  "tipik": "particle",
  "tulo": "leakage",
  "tumanglaw": "illumine",
  "tunga": "half",
  "umepapasa-papasa": "expired-papasa",
  "unahan": "fore",
  "wala": "nothing",
  "walo": "eight",
  "şaha": "sheath"
 }
}